imap_structure/__init__.py
imap_structure/body_structure.py
imap_structure/metadata.py
imap_structure/parser.py
imap_structure-0.2.0.dist-info/METADATA
imap_structure-0.2.0.dist-info/WHEEL
imap_structure-0.2.0.dist-info/RECORD
