Metadata-Version: 2.1
Name: imap-structure
Version: 0.2.0
Summary: IMAP BODYSTRUCTURE parser
Home-page: https://github.com/KiruyaMomochi/pyimap-structure
Author: Kiruya Momochi
Author-email: 65301509+kiruyamomochi@users.noreply.github.com
Requires-Python: >=3.10,<4.0
Classifier: Programming Language :: Python :: 3
Classifier: Programming Language :: Python :: 3.10
Classifier: Programming Language :: Python :: 3.11
Requires-Dist: pyparsing (>=3.0.9,<4.0.0)
